ms_identity_web/__init__.py
ms_identity_web/adapters.py
ms_identity_web/configuration.py
ms_identity_web/constants.py
ms_identity_web/context.py
ms_identity_web/errors.py
ms_identity_web/django/__init__.py
ms_identity_web/django/adapter.py
ms_identity_web/django/middleware.py
ms_identity_web/django/msal_views_and_urls.py
ms_identity_web/flask_blueprint/__init__.py
ms_identity_web-0.0.3.dist-info/METADATA
ms_identity_web-0.0.3.dist-info/WHEEL
ms_identity_web-0.0.3.dist-info/licenses/LICENSE
ms_identity_web-0.0.3.dist-info/licenses/LICENSE.md
ms_identity_web-0.0.3.dist-info/RECORD
