Metadata-Version: 2.1
Name: ms-identity-web
Version: 0.0.3
Summary: Autenticación Azure DA
Project-URL: Homepage, https://github.com/aabedoya/ms-identity-web/
Project-URL: Bug Tracker, https://github.com/aabedoya/ms-identity-web/issues
Author-email: Alvaro Andres Bedoya <andresbedoyagomez@gmail.com>
License: MIT License
License-File: LICENSE
License-File: LICENSE.md
Classifier: License :: OSI Approved :: MIT License
Classifier: Operating System :: OS Independent
Classifier: Programming Language :: Python :: 3
Requires-Python: >=3.8
